aci/__init__.py
aci/_client.py
aci/_constants.py
aci/_exceptions.py
aci/libs/__init__.py
aci/libs/_compatible_schema.py
aci/libs/_function_schema.py
aci/libs/_tool.py
aci/meta_functions/__init__.py
aci/meta_functions/_aci_execute_function.py
aci/meta_functions/_aci_search_functions.py
aci/meta_functions/_base.py
aci/resource/__init__.py
aci/resource/_base.py
aci/resource/app_configurations.py
aci/resource/apps.py
aci/resource/functions.py
aci/resource/linked_accounts.py
aci/types/__init__.py
aci/types/app_configurations.py
aci/types/apps.py
aci/types/enums.py
aci/types/functions.py
aci/types/linked_accounts.py
aci/utils/__init__.py
aci/utils/_logging.py
aci/utils/_type_check.py
aci/py.typed
aci_sdk-1.0.0b4.dist-info/METADATA
aci_sdk-1.0.0b4.dist-info/WHEEL
aci_sdk-1.0.0b4.dist-info/licenses/LICENSE
aci_sdk-1.0.0b4.dist-info/RECORD
