Metadata-Version: 2.4
Name: aci-sdk
Version: 1.0.0b4
Summary: The Python SDK for the Agent Computer Interface (ACI) by Aipotheosis Labs
Author-email: Aipolabs <support@aipolabs.xyz>
Maintainer-email: Aipolabs <support@aipolabs.xyz>
License-File: LICENSE
Keywords: ACI,API,Agent Computer Interface,Aipolabs,Aipotheosis Labs,Function Calling,LLM,MCP,Tool Calling
Classifier: Development Status :: 4 - Beta
Classifier: Intended Audience :: Developers
Classifier: Operating System :: MacOS
Classifier: Operating System :: Microsoft :: Windows
Classifier: Operating System :: OS Independent
Classifier: Operating System :: POSIX
Classifier: Operating System :: POSIX :: Linux
Classifier: Programming Language :: Python :: 3.10
Classifier: Programming Language :: Python :: 3.11
Classifier: Programming Language :: Python :: 3.12
Classifier: Programming Language :: Python :: 3.13
Classifier: Topic :: Software Development :: Libraries :: Python Modules
Classifier: Typing :: Typed
Requires-Python: >=3.10
Requires-Dist: griffe>=1.7.2
Requires-Dist: httpx>=0.27.2
Requires-Dist: pydantic>=2.11.3
Requires-Dist: tenacity>=8.2.3
Requires-Dist: typing-extensions>=4.13.2
